pykit_tools/__init__.py
pykit_tools/cmd.py
pykit_tools/str_tool.py
pykit_tools/utils.py
pykit_tools/decorators/__init__.py
pykit_tools/decorators/cache.py
pykit_tools/decorators/common.py
pykit_tools/decorators/req_utils.py
pykit_tools/log/__init__.py
pykit_tools/log/adapter.py
pykit_tools/log/handlers.py
pykit_tools/patterns/__init__.py
pykit_tools/patterns/singleton.py
pykit_tools-1.2.4.dist-info/LICENSE
pykit_tools-1.2.4.dist-info/METADATA
pykit_tools-1.2.4.dist-info/WHEEL
pykit_tools-1.2.4.dist-info/top_level.txt
pykit_tools-1.2.4.dist-info/RECORD
