Metadata-Version: 2.1
Name: pykit-tools
Version: 1.2.4
Summary: python tools
Home-page: https://github.com/SkylerHu/pykit-tools.git
Author: SkylerHu
Author-email: skylerhu@qq.com
License: MIT Licence
Keywords: python,tools,utils,py-tools,pykit-tools,py-toolkit,py-utils
Platform: any
Classifier: Development Status :: 4 - Beta
Classifier: Intended Audience :: Developers
Classifier: License :: OSI Approved :: MIT License
Classifier: Programming Language :: Python :: 3
Classifier: Programming Language :: Python :: 3 :: Only
Classifier: Programming Language :: Python :: 3.9
Classifier: Programming Language :: Python :: 3.10
Classifier: Programming Language :: Python :: 3.11
Classifier: Programming Language :: Python :: 3.12
Classifier: Programming Language :: Python :: Implementation :: CPython
Requires-Python: >=3.6
License-File: LICENSE
Requires-Dist: py-enum >=2.1.1
Provides-Extra: redis
Requires-Dist: redis >=2.10.3 ; extra == 'redis'
